mgvestruc/__init__.py
mgvestruc/analisis_geometrico.py
mgvestruc/curva_interaccion.py
mgvestruc/tests.py
mgvestruc-1.0.0.dist-info/LICENSE
mgvestruc-1.0.0.dist-info/METADATA
mgvestruc-1.0.0.dist-info/WHEEL
mgvestruc-1.0.0.dist-info/top_level.txt
mgvestruc-1.0.0.dist-info/RECORD
