Metadata-Version: 2.1
Name: mgvestruc
Version: 1.0.0
Summary: Funciones de aplicación en Ingeniería Estructural
Home-page: UNKNOWN
Author: Matías Glasner
Author-email: mglasner10@gmail.com
License: UNKNOWN
Platform: UNKNOWN
Classifier: Programming Language :: Python :: 3
Classifier: License :: OSI Approved :: MIT License
Classifier: Operating System :: OS Independent
Requires-Dist: numpy
